{
  "$schema": "https://schema.management.azure.com/schemas/2015-01-01/deploymentTemplate.json#",
  "contentVersion": "1.0.0.0",
  "parameters": {
    "newStorageAccountName": {
      "type": "string",
      "metadata": {
        "description": "Unique DNS Name for the Storage Account where the Virtual Machine's disks will be placed."
      }
    },
    "adminUsername": {
      "type": "string",
      "metadata": {
        "description": "Username for the Virtual Machine."
      }
    },
    "adminPassword": {
      "type": "securestring",
      "metadata": {
        "description": "Password for the Virtual Machine."
      }
    },
    "publicIPAddressName": {
      "type": "string",
      "metadata": {
        "description": "Unique DNS Name for the Public IP used to access the Virtual Machine."
      }
    },
    "vmSize": {
      "type": "string",
      "defaultValue": "Standard_A2",
      "allowedValues": [
        "Standard_A1",
        "Standard_A2",
        "Standard_A3",
        "Standard_A4",
        "Standard_D1",
        "Standard_D2",
        "Standard_D3",
        "Standard_D4"
      ],
      "metadata": {
        "description": "Size of vm"
      }	  
    }
  },
  "variables": {
    "nicName": "myVMNic",
    "addressPrefix": "10.0.0.0/16",
    "subnetName": "Subnet",
    "subnetPrefix": "10.0.0.0/24",
    "publicIPAddressType": "Dynamic",
    "vmStorageAccountContainerName": "vhds",
    "vmName": "SiebelDemoVM",
    "virtualNetworkName": "MyVNET",
    "vnetID": "[resourceId('Microsoft.Network/virtualNetworks',variables('virtualNetworkName'))]",
    "subnetRef": "[concat(variables('vnetID'),'/subnets/',variables('subnetName'))]"
  },
  "resources": [
    {
      "type": "Microsoft.Storage/storageAccounts",
      "name": "[parameters('newStorageAccountName')]",
      "apiVersion": "2015-05-01-preview",
      "location": "[resourceGroup().location]",
      "tags": {
        "displayName": "StorageAccount"
      },
      "properties": {
        "accountType": "Standard_LRS"
      }
    },
    {
      "apiVersion": "2015-05-01-preview",
      "type": "Microsoft.Network/publicIPAddresses",
      "name": "[parameters('publicIPAddressName')]",
      "location": "[resourceGroup().location]",
      "tags": {
        "displayName": "PublicIPAddress"
      },
      "properties": {
        "publicIPAllocationMethod": "[variables('publicIPAddressType')]",
        "dnsSettings": {
          "domainNameLabel": "[parameters('publicIPAddressName')]"
        }
      }
    },
    {
      "apiVersion": "2015-05-01-preview",
      "type": "Microsoft.Network/virtualNetworks",
      "name": "[variables('virtualNetworkName')]",
      "location": "[resourceGroup().location]",
      "tags": {
        "displayName": "VirtualNetwork"
      },
      "properties": {
        "addressSpace": {
          "addressPrefixes": [
            "[variables('addressPrefix')]"
          ]
        },
        "subnets": [
          {
            "name": "[variables('subnetName')]",
            "properties": {
              "addressPrefix": "[variables('subnetPrefix')]"
            }
          }
        ]
      }
    },
    {
      "apiVersion": "2015-05-01-preview",
      "type": "Microsoft.Network/networkInterfaces",
      "name": "[variables('nicName')]",
      "location": "[resourceGroup().location]",
      "tags": {
        "displayName": "NetworkInterface"
      },
      "dependsOn": [
        "[concat('Microsoft.Network/publicIPAddresses/', parameters('publicIPAddressName'))]",
        "[concat('Microsoft.Network/virtualNetworks/', variables('virtualNetworkName'))]"
      ],
      "properties": {
        "ipConfigurations": [
          {
            "name": "ipconfig1",
            "properties": {
              "privateIPAllocationMethod": "Dynamic",
              "publicIPAddress": {
                "id": "[resourceId('Microsoft.Network/publicIPAddresses',parameters('publicIPAddressName'))]"
              },
              "subnet": {
                "id": "[variables('subnetRef')]"
              }
            }
          }
        ]
      }
    },
    {
      "apiVersion": "2015-06-15",
      "name": "[variables('vmName')]",
      "type": "Microsoft.Compute/virtualMachines",
      "location": "[resourceGroup().location]",
      "dependsOn": [
        "[concat('Microsoft.Storage/storageAccounts/', parameters('newStorageAccountName'))]",
        "[concat('Microsoft.Network/networkInterfaces/', variables('nicName'))]"
      ],
      "properties": {
        "hardwareProfile": {
          "vmSize": "[parameters('vmSize')]"
        },
        "storageProfile": {
          "osDisk": {
            "osType": "Windows",
            "name": "OSDisk",
            "createOption": "FromImage",
            "image": {  
              "uri": "[concat('http://',parameters('newStorageAccountName'),'.blob.core.windows.net/images/Microsoft.Compute/Images/singlevm/vm-osDisk.a7d14edf-ec73-4556-923b-30d7fff83272.vhd')]"
            },
            "vhd": {
              "uri": "[concat('http://',parameters('newStorageAccountName'),'.blob.core.windows.net/',variables('vmStorageAccountContainerName'),'/','siebel1os.vhd')]"
            },
            "caching": "ReadWrite"
          }
        },
        "osProfile": {
          "computerName": "[variables('vmName')]",
          "adminUsername": "[parameters('adminUsername')]",
          "adminPassword": "[parameters('adminPassword')]"
        },
        "networkProfile": {
          "networkInterfaces": [
            {
              "id": "[resourceId('Microsoft.Network/networkInterfaces',variables('nicName'))]"
            }
          ]
        },
        "provisioningState": 0
      }
    }
  ]
}
